telegraf_xiaomi_air_purifier-0.2.0.data/scripts/telegraf-xiaomi-air-purifier
telegraf_xiaomi_air_purifier-0.2.0.dist-info/METADATA
telegraf_xiaomi_air_purifier-0.2.0.dist-info/RECORD
telegraf_xiaomi_air_purifier-0.2.0.dist-info/WHEEL
telegraf_xiaomi_air_purifier-0.2.0.dist-info/top_level.txt
xiaomi/__init__.py
xiaomi/xiaomi_air_purifier.py
