Metadata-Version: 2.1
Name: telegraf-xiaomi-air-purifier
Version: 0.2.0
Summary: Telegraf plugin for Xiaomi Air Purifier
Home-page: https://github.com/SebastianCzoch/telegraf-xiaomi-air-purifier
Author: Sebastian Czoch
Author-email: sebastian@czoch.pl
License: MIT
Platform: UNKNOWN
Classifier: Development Status :: 4 - Beta
Classifier: Intended Audience :: System Administrators
Classifier: License :: OSI Approved :: MIT License
Classifier: Programming Language :: Python :: 3 :: Only
Classifier: Operating System :: OS Independent
Requires-Dist: influx-line-protocol (>=0.1.0)
Requires-Dist: python-miio (>=0.4.2)
